LICENSE
README.md
setup.py
procgen/__init__.py
procgen/builder.py
procgen/env.py
procgen/env_test.py
procgen/gym_registration.py
procgen/interactive.py
procgen/state_test.py
procgen/version.txt
procgen/data/assets/kenney-abstract/Backgrounds/set1_background.png
procgen/data/assets/kenney-abstract/Backgrounds/set1_hills.png
procgen/data/assets/kenney-abstract/Backgrounds/set1_tiles.png
procgen/data/assets/kenney-abstract/Backgrounds/set2_background.png
procgen/data/assets/kenney-abstract/Backgrounds/set2_hills.png
procgen/data/assets/kenney-abstract/Backgrounds/set2_tiles.png
procgen/data/assets/kenney-abstract/Backgrounds/set3_background.png
procgen/data/assets/kenney-abstract/Backgrounds/set3_hills.png
procgen/data/assets/kenney-abstract/Backgrounds/set3_tiles.png
procgen/data/assets/kenney-abstract/Backgrounds/set4_background.png
procgen/data/assets/kenney-abstract/Backgrounds/set4_hills.png
procgen/data/assets/kenney-abstract/Backgrounds/set4_tiles.png
procgen/data/assets/kenney-abstract/Enemies/enemyFloating_1.png
procgen/data/assets/kenney-abstract/Enemies/enemyFloating_2.png
procgen/data/assets/kenney-abstract/Enemies/enemyFloating_3.png
procgen/data/assets/kenney-abstract/Enemies/enemyFloating_4.png
procgen/data/assets/kenney-abstract/Enemies/enemyFlyingAlt_1.png
procgen/data/assets/kenney-abstract/Enemies/enemyFlyingAlt_2.png
procgen/data/assets/kenney-abstract/Enemies/enemyFlyingAlt_3.png
procgen/data/assets/kenney-abstract/Enemies/enemyFlyingAlt_4.png
procgen/data/assets/kenney-abstract/Enemies/enemyFlying_1.png
procgen/data/assets/kenney-abstract/Enemies/enemyFlying_2.png
procgen/data/assets/kenney-abstract/Enemies/enemyFlying_3.png
procgen/data/assets/kenney-abstract/Enemies/enemyFlying_4.png
procgen/data/assets/kenney-abstract/Enemies/enemySpikey_1.png
procgen/data/assets/kenney-abstract/Enemies/enemySpikey_2.png
procgen/data/assets/kenney-abstract/Enemies/enemySpikey_3.png
procgen/data/assets/kenney-abstract/Enemies/enemySpikey_4.png
pufferai_procgen.egg-info/PKG-INFO
pufferai_procgen.egg-info/SOURCES.txt
pufferai_procgen.egg-info/dependency_links.txt
pufferai_procgen.egg-info/requires.txt
pufferai_procgen.egg-info/top_level.txt