Metadata-Version: 2.1
Name: pufferai_procgen
Version: 0.10.7.0
Summary: Procedurally Generated Game-Like RL Environments
Home-page: https://github.com/openai/procgen
Author: OpenAI
Requires-Python: >=3.6.0
License-File: LICENSE
Requires-Dist: numpy<2.0.0,>=1.17.0
Requires-Dist: gym<1.0.0,>=0.15.0
Requires-Dist: pufferai-gym3<1.0.0,>=0.3.3.2
Requires-Dist: filelock<4.0.0,>=3.0.0
Provides-Extra: test
Requires-Dist: pytest==6.2.5; extra == "test"
Requires-Dist: pytest-benchmark==3.4.1; extra == "test"
